chargebee/__init__.py
chargebee/api_error.py
chargebee/compat.py
chargebee/environment.py
chargebee/http_request.py
chargebee/main.py
chargebee/model.py
chargebee/request.py
chargebee/response.py
chargebee/responses.py
chargebee/retry_config.py
chargebee/util.py
chargebee/version.py
chargebee/filters/__init__.py
chargebee/filters/filters.py
chargebee/models/__init__.py
chargebee/models/enums.py
chargebee/models/addon/__init__.py
chargebee/models/addon/operations.py
chargebee/models/addon/responses.py
chargebee/models/address/__init__.py
chargebee/models/address/operations.py
chargebee/models/address/responses.py
chargebee/models/advance_invoice_schedule/__init__.py
chargebee/models/advance_invoice_schedule/operations.py
chargebee/models/advance_invoice_schedule/responses.py
chargebee/models/attached_item/__init__.py
chargebee/models/attached_item/operations.py
chargebee/models/attached_item/responses.py
chargebee/models/attribute/__init__.py
chargebee/models/attribute/operations.py
chargebee/models/attribute/responses.py
chargebee/models/billing_configuration/__init__.py
chargebee/models/billing_configuration/operations.py
chargebee/models/billing_configuration/responses.py
chargebee/models/brand/__init__.py
chargebee/models/brand/operations.py
chargebee/models/brand/responses.py
chargebee/models/business_entity/__init__.py
chargebee/models/business_entity/operations.py
chargebee/models/business_entity/responses.py
chargebee/models/business_entity_transfer/__init__.py
chargebee/models/business_entity_transfer/operations.py
chargebee/models/business_entity_transfer/responses.py
chargebee/models/card/__init__.py
chargebee/models/card/operations.py
chargebee/models/card/responses.py
chargebee/models/comment/__init__.py
chargebee/models/comment/operations.py
chargebee/models/comment/responses.py
chargebee/models/configuration/__init__.py
chargebee/models/configuration/operations.py
chargebee/models/configuration/responses.py
chargebee/models/contact/__init__.py
chargebee-3.15.0.dist-info/licenses/LICENSE
chargebee-3.15.0.dist-info/METADATA
chargebee-3.15.0.dist-info/WHEEL
chargebee-3.15.0.dist-info/top_level.txt
chargebee-3.15.0.dist-info/RECORD
