Metadata-Version: 2.4
Name: chargebee
Version: 3.15.0
Summary: Python wrapper for the Chargebee Subscription Billing API
Home-page: https://apidocs.chargebee.com/docs/api?lang=python
Author: Chargebee
Author-email: dx@chargebee.com
Requires-Python: >=3.11
License-File: LICENSE
Requires-Dist: httpx
Dynamic: author
Dynamic: author-email
Dynamic: description
Dynamic: description-content-type
Dynamic: home-page
Dynamic: license-file
Dynamic: requires-dist
Dynamic: requires-python
Dynamic: summary
